{
  "type": "appart",
  "photos": [],
  "_saved": "2026-05-25T10:15:42.811Z",
  "gh-token-input": "",
  "proprio_prenom": "Yakhouba",
  "proprio_nom": "TIMERA",
  "date_r1": "2025-11-14",
  "tel_fixe": "",
  "tel_mobile": "06 98 31 97 96",
  "email": "yakhoubatimera@yahoo.fr",
  "adresse": "11 Résidence de la Croix Blanche 91380 Chilly Mazarin",
  "raison_vente": "actuellement loué et n'est plus rentable à cause du montant des charges",
  "annee_achat": "",
  "prix_achat": "",
  "capital_restant": "",
  "delai_vente": "tout de suite",
  "vente_depuis": "1.5 an",
  "nb_visites": "30",
  "nb_offres": "0",
  "prix_offres": "",
  "agences": "que moi maintenant",
  "cles_chez": "locataires",
  "loyer": "1200",
  "scenario_montant": "",
  "scenario_reponse": "doit 134 000€ à la banque mais veux s'en débarrasser et fera un effort",
  "surface_hab": "65",
  "surface_carrez": "64.73",
  "surface_terrain": "",
  "surface_terrain_m": "",
  "volume_bat": "",
  "nb_pieces": "3",
  "nb_chambres": "2",
  "nb_sdb": "1",
  "nb_wc": "",
  "nb_sde": "",
  "nb_wc_sep": "1",
  "etage": "3",
  "nb_etages": "3",
  "annee_construction": "1970",
  "syndic_nom": "",
  "travaux_ag_detail": "Ravalement va être voté en Juin 2026",
  "travaux_recents_immeuble": "",
  "annee_construction_m": "",
  "nb_etages_m": "",
  "standard_general": "",
  "prix_vente": "145000",
  "taxe_fonciere": "1079",
  "taxe_hab": "",
  "charges_copro": "345",
  "charges_mensuelles": "",
  "plus_appartement": "",
  "parking_int": "",
  "parking_ext": "1",
  "parking_box": "",
  "toit_type_autre_txt": "",
  "facade_type_autre_txt": "",
  "sols_type_autre_txt": "",
  "chauf_diffusion_autre_txt": "",
  "chauf_annee": "",
  "ecs_autre_txt": "",
  "travaux_recents": "Le propriétaire va refaire un coup de propre dès que les locataires sortent. \nActu : travaux à prévoir : sols, peintures, cuisine",
  "equip_autre": "",
  "ext_Jardin_m2": "",
  "ext_Jardin_d_hiver_m2": "",
  "ext_Terrasse_m2": "",
  "ext_Balcon_s__m2": "4",
  "ext_Piscine_m2": "",
  "ext_Pelouse_m2": "",
  "plus_bien": "Dernier étage sans vis-à-vis + balcon Sud-Ouest\nRavalement voté et pris en charge par le propriétaire\nRésidence avec gardien, tennis, espaces verts\nMeilleur rapport qualité / prix du moment\n",
  "vigilances_texte": "Travaux de rafraîchissement à prévoir\nCharges de copropriété : 345€ (tout compris)\n",
  "exposition_autre_txt": "",
  "transport_autre_txt": "",
  "services_prox": "2coles, commerces, A6, bus",
  "voisinage": "Résidentiel, calme",
  "dpe_valeur": "269",
  "ges_valeur": "58",
  "syndic_copro": "",
  "dette_montant": "",
  "dette_echeance": "",
  "banque": "",
  "taux_pret": "",
  "reloge_budget": "",
  "reloge_type": "",
  "reloge_delai": "",
  "reloge_zone": "",
  "reloge_pieces": "",
  "zone_plu": "",
  "superficie_totale": "",
  "superficie_constructible": "",
  "forme_terrain": "",
  "acces_terrain": "",
  "cos_ces": "",
  "hauteur_max": "",
  "t_nord": "on",
  "t_sud": "on",
  "t_est": "on",
  "t_ouest": "on",
  "projet_terrain": "",
  "prix_vente_t": "",
  "taxe_fonciere_t": "",
  "dvf_cp": "91380",
  "dvf_type": "Appartement",
  "photo_input": "",
  "q1": "",
  "q2": "",
  "q3": "",
  "q4": "",
  "q5": "",
  "notes_libres": "",
  "prochaines_etapes": "",
  "date_r2": "",
  "radio_utilisation": "location",
  "radio_ascenseur": "non",
  "radio_travaux_ag": "oui",
  "radio_copro": "oui",
  "radio_pu_Sous_sol": "non",
  "radio_pu_Cave": "oui",
  "radio_pu_Grenier": "non",
  "radio_pu_Cave___vin": "non",
  "radio_pu_Local_de_rangement": "non",
  "radio_pu_Salle_de_loisirs": "non",
  "radio_pu_Combles": "non",
  "radio_pu_D_pendances": "non",
  "radio_vitrage_type": "Double vitrage",
  "radio_volets_elec": "non",
  "radio_chauf_type": "Collectif",
  "radio_ecs": "Gaz",
  "radio_defaut_Moisissures": "non",
  "radio_defaut_Fissures": "non",
  "radio_defaut_Remont_es_capillaires": "non",
  "radio_defaut_Insectes_nuisibles": "non",
  "radio_defaut_D_g_ts_d_eau": "non",
  "radio_defaut_C_bles_haute_tension": "non",
  "radio_defaut_Antenne_t_l_phonie_mobile": "non",
  "radio_defaut_Amiante": "non",
  "radio_eg_Chemin_e": "non",
  "radio_eg_Po_le": "non",
  "radio_eg_Sauna": "non",
  "radio_eg_Photovolta_que": "non",
  "radio_eg_Jacuzzi___Whirlpool": "non",
  "radio_eg_Ascenseur": "non",
  "radio_eg_Piscine_int_rieure": "non",
  "radio_eg_Solaire_thermique": "non",
  "radio_plaque_cuisson": "Induction",
  "radio_ec_Four": "oui",
  "radio_ec_Steamer": "non",
  "radio_ec_Cong_lateur": "non",
  "radio_ec_Lave_vaisselle": "non",
  "radio_ec_R_frig_rateur": "non",
  "radio_ec_Cave___vin": "non",
  "radio_ext_Jardin": "non",
  "radio_ext_Jardin_d_hiver": "non",
  "radio_ext_Terrasse": "non",
  "radio_ext_Vue": "non",
  "radio_ext_Balcon_s_": "oui",
  "radio_ext_Piscine": "non",
  "radio_ext_Pelouse": "non",
  "radio_ext_Portail": "non",
  "radio_vigi_Nuisances_sonores": "non",
  "radio_vigi_Vis___vis_direct": "non",
  "radio_vigi_Humidit__r_currente": "non",
  "radio_vigi_Travaux_importants___pr_voir": "non",
  "radio_vigi_Isolation_thermique_insuffisante": "non",
  "radio_vigi_Parties_communes_d_grad_es": "non",
  "radio_vigi_Environnement_en_mutation": "non",
  "radio_vigi_Servitude_de_passage": "non",
  "radio_vigi_Litige_de_voisinage": "non",
  "radio_vigi_Toit___toiture___refaire": "non",
  "radio_vigi_Fen_tres___changer": "non",
  "radio_vigi_Chauffage_v_tuste": "non",
  "radio_vigi__lectricit____mettre_aux_normes": "non",
  "radio_expo_sonore": "Normal",
  "radio_servitudes": "non",
  "radio_droits_superf": "non",
  "radio_relogement_trouve": "oui",
  "radio_viab_Eau": "non",
  "radio_viab_Électricité": "non",
  "radio_viab_Gaz": "non",
  "radio_viab_Assainissement": "non",
  "radio_viab_Fibre optique": "non",
  "radio_risque_Zone_inondable": "non",
  "radio_risque_Sol_argileux": "non",
  "radio_risque_Zone_sismique": "non",
  "radio_risque_Ligne_haute_tension": "non",
  "radio_risque_Servitude": "non",
  "cb_t_nord": false,
  "cb_t_sud": false,
  "cb_t_est": false,
  "cb_t_ouest": false,
  "rating_sols_etat": "Moyen",
  "rating_etat_general": "Moyen",
  "dpe_dpe": "E",
  "dpe_ges": "E",
  "_pieces_table": [
    [
      "Entrée",
      "",
      "",
      ""
    ],
    [
      "Séjour",
      "",
      "",
      ""
    ],
    [
      "Salle à manger",
      "",
      "",
      ""
    ],
    [
      "Chambre 1",
      "",
      "",
      ""
    ],
    [
      "Chambre 2",
      "",
      "",
      ""
    ],
    [
      "Chambre 3",
      "",
      "",
      ""
    ],
    [
      "Chambre 4",
      "",
      "",
      ""
    ],
    [
      "Chambre 5",
      "",
      "",
      ""
    ],
    [
      "Cuisine",
      "",
      "",
      ""
    ],
    [
      "WC",
      "",
      "",
      ""
    ],
    [
      "Salle de bains",
      "",
      "",
      ""
    ],
    [
      "Salle d'eau",
      "",
      "",
      ""
    ],
    [
      "",
      "",
      "",
      ""
    ],
    [
      "",
      "",
      "",
      ""
    ]
  ],
  "plaque_cuisson": "Induction"
}